adema/__init__.py
adema/cli.py
adema/base/__init__.py
adema/base/admin.py
adema/base/agents.py
adema/base/apps.py
adema/base/models.py
adema/base/services.py
adema/generator/__init__.py
adema/generator/model_builder.py
adema/generator/project_builder.py
adema/modules/__init__.py
adema/modules/base.py
adema/modules/config.py
adema/modules/registry.py
adema/templates/__init__.py
adema/templates/app_template/__init__.py-tpl
adema/templates/app_template/apps.py-tpl
adema/templates/app_template/models.py-tpl
adema/templates/app_template/urls.py-tpl
adema/templates/app_template/admin/__init__.py
adema/templates/app_template/admin/dashboard.py
adema/templates/app_template/components/__init__.py
adema/templates/app_template/components/example_model.py-tpl
adema/templates/app_template/migrations/__init__.py
adema/templates/app_template/services/__init__.py
adema/templates/app_template/views/__init__.py
adema/templates/project_template/.env.example
adema/templates/project_template/manage.py-tpl
adema/templates/project_template/requirements.txt
adema/templates/project_template/config/__init__.py
adema/templates/project_template/config/asgi.py
adema/templates/project_template/config/urls.py
adema/templates/project_template/config/wsgi.py
adema/templates/project_template/config/settings/__init__.py
adema/templates/project_template/config/settings/base.py-tpl
adema/templates/project_template/config/settings/local.py-tpl
adema/templates/project_template/config/settings/production.py-tpl
adema/ui/__init__.py
adema/ui/server.py
adema/ui/static/css/wizard.css
adema/ui/static/js/wizard.js
adema/ui/templates/wizard.html
adema/utils/__init__.py
adema/utils/env.py
django_adema-0.1.0.dist-info/licenses/LICENSE
django_adema-0.1.0.dist-info/METADATA
django_adema-0.1.0.dist-info/WHEEL
django_adema-0.1.0.dist-info/entry_points.txt
django_adema-0.1.0.dist-info/top_level.txt
django_adema-0.1.0.dist-info/RECORD
