Metadata-Version: 2.4
Name: django-adema
Version: 0.1.0
Summary: Django meta-framework for generating ERP/CRM projects with Vertical Slicing architecture
Home-page: https://github.com/Excel-ente/django-adema
Author: ADEMA Team
Author-email: ADEMA Team <info@adema.dev>
Maintainer-email: Excel-ente <info@adema.dev>
License: MIT
Project-URL: Homepage, https://github.com/Excel-ente/django-adema
Project-URL: Documentation, https://github.com/Excel-ente/django-adema#readme
Project-URL: Repository, https://github.com/Excel-ente/django-adema
Project-URL: Issues, https://github.com/Excel-ente/django-adema/issues
Keywords: django,framework,erp,crm,scaffolding,generator,vertical-slicing,cli,wizard
Classifier: Development Status :: 3 - Alpha
Classifier: Environment :: Console
Classifier: Environment :: Web Environment
Classifier: Framework :: Django :: 4.2
Classifier: Intended Audience :: Developers
Classifier: License :: OSI Approved :: MIT License
Classifier: Operating System :: OS Independent
Classifier: Programming Language :: Python :: 3
Classifier: Programming Language :: Python :: 3.9
Classifier: Programming Language :: Python :: 3.10
Classifier: Programming Language :: Python :: 3.11
Classifier: Programming Language :: Python :: 3.12
Classifier: Topic :: Software Development :: Code Generators
Classifier: Topic :: Internet :: WWW/HTTP :: Dynamic Content
Requires-Python: >=3.9
License-File: LICENSE
Requires-Dist: Django>=4.2
Requires-Dist: python-dotenv>=1.0.0
Requires-Dist: psycopg2-binary>=2.9.9
Requires-Dist: typer[all]>=0.9.0
Requires-Dist: rich>=13.0.0
Requires-Dist: fastapi>=0.104.0
Requires-Dist: uvicorn[standard]>=0.24.0
Requires-Dist: Jinja2>=3.1.2
Provides-Extra: dev
Requires-Dist: black; extra == "dev"
Requires-Dist: isort; extra == "dev"
Requires-Dist: flake8; extra == "dev"
Requires-Dist: pytest; extra == "dev"
Requires-Dist: pytest-django; extra == "dev"
Requires-Dist: pytest-cov; extra == "dev"
Requires-Dist: mypy; extra == "dev"
Requires-Dist: django-stubs; extra == "dev"
Requires-Dist: twine; extra == "dev"
Requires-Dist: build; extra == "dev"
Dynamic: author
Dynamic: home-page
Dynamic: license-file
Dynamic: requires-python
